problems/2025/00_signext/verilog.00/a.v
module sign_extention_a #(parameter N = 12, parameter M = 32)
    (
    input wire [N - 1: 0] i_x,
    output wire [M - 1: 0] o_y
    );

assign o_y[N - 1: 0] = i_x;
assign o_y[M - 1: N] = {M-N{i_x[N - 1]}};

endmodule

homework/verilog.00/testbench_a.v
`timescale 1ns/1ps

module sign_extention_a_TB;

localparam N = 12;
localparam M = 32;

wire [M - 1: 0] y;
reg [N - 1: 0] x = {N{1'b0}};

always begin

    #1 if (x == y[N - 1 :0]) begin
        if (y[M - 1 :N] == {M - N{x[N - 1]}})
            $display("[%t] x=%b y=%b OK", $realtime, x, y);
        else
            $display("[%t] x=%b y=%b FAIL", $realtime, x, y);
    end
    else 
        $display("[%t] x=%b y=%b FAIL", $realtime, x, y);
    #1 x = x + 1;
    if (x == {N{1'b1}}) begin
        $display("[%t] Done", $realtime);
        $finish;
    end
end

sign_extention_a #(.N(N)) sign_extention_a_inst(.i_x(x), .o_y(y));

initial begin
    $dumpvars;
    $display("[%t] Start", $realtime);
end

endmodule

problems/2025/00_signext/verilog.00/dump.vcd
$date
	Wed Feb 12 23:40:26 2025
$end
$version
	Icarus Verilog
$end
$timescale
	1ps
$end
$scope module sign_extention_a_TB $end
$var wire 32 ! y [31:0] $end
$var reg 12 " x [11:0] $end
$scope module sign_extention_a_inst $end
$var wire 12 # i_x [11:0] $end
$var wire 32 $ o_y [31:0] $end
$scope begin gen_sign_extention1s[0] $end
$scope module sign_extention_a_inst $end
$var wire 1 % i_x $end
$var wire 1 & o_y $end
$upscope $end
$upscope $end
$scope begin gen_sign_extention1s[1] $end
$scope module sign_extention_a_inst $end
$var wire 1 ' i_x $end
$var wire 1 ( o_y $end
$upscope $end
$upscope $end
$scope begin gen_sign_extention1s[2] $end
$scope module sign_extention_a_inst $end
$var wire 1 ) i_x $end
$var wire 1 * o_y $end
$upscope $end
$upscope $end
$scope begin gen_sign_extention1s[3] $end
$scope module sign_extention_a_inst $end
$var wire 1 + i_x $end
$var wire 1 , o_y $end
$upscope $end
$upscope $end
$scope begin gen_sign_extention1s[4] $end
$scope module sign_extention_a_inst $end
$var wire 1 - i_x $end
$var wire 1 . o_y $end
$upscope $end
$upscope $end
$scope begin gen_sign_extention1s[5] $end
$scope module sign_extention_a_inst $end
$var wire 1 / i_x $end
$var wire 1 0 o_y $end
$upscope $end
$upscope $end
$scope begin gen_sign_extention1s[6] $end
$scope module sign_extention_a_inst $end
$var wire 1 1 i_x $end
$var wire 1 2 o_y $end
$upscope $end
$upscope $end
$scope begin gen_sign_extention1s[7] $end
$scope module sign_extention_a_inst $end
$var wire 1 3 i_x $end
$var wire 1 4 o_y $end
$upscope $end
$upscope $end
$scope begin gen_sign_extention1s[8] $end
$scope module sign_extention_a_inst $end
$var wire 1 5 i_x $end
$var wire 1 6 o_y $end
$upscope $end
$upscope $end
$scope begin gen_sign_extention1s[9] $end
$scope module sign_extention_a_inst $end
$var wire 1 7 i_x $end
$var wire 1 8 o_y $end
$upscope $end
$upscope $end
$scope begin gen_sign_extention1s[10] $end
$scope module sign_extention_a_inst $end
$var wire 1 9 i_x $end
$var wire 1 : o_y $end
$upscope $end
$upscope $end
$scope begin gen_sign_extention1s[11] $end
$scope module sign_extention_a_inst $end
$var wire 1 ; i_x $end
$var wire 1 < o_y $end
$upscope $end
$upscope $end
$scope begin gen_sign_extention1ss[12] $end
$scope module sign_extention_a_inst $end
$var wire 1 = i_x $end
$var wire 1 > o_y $end
$upscope $end
$upscope $end
$scope begin gen_sign_extention1ss[13] $end
$scope module sign_extention_a_inst $end
$var wire 1 ? i_x $end
$var wire 1 @ o_y $end
$upscope $end
$upscope $end
$scope begin gen_sign_extention1ss[14] $end
$scope module sign_extention_a_inst $end
$var wire 1 A i_x $end
$var wire 1 B o_y $end
$upscope $end
$upscope $end
$scope begin gen_sign_extention1ss[15] $end
$scope module sign_extention_a_inst $end
$var wire 1 C i_x $end
$var wire 1 D o_y $end
$upscope $end
$upscope $end
$scope begin gen_sign_extention1ss[16] $end
$scope module sign_extention_a_inst $end
$var wire 1 E i_x $end
$var wire 1 F o_y $end
$upscope $end
$upscope $end
$scope begin gen_sign_extention1ss[17] $end
$scope module sign_extention_a_inst $end
$var wire 1 G i_x $end
$var wire 1 H o_y $end
$upscope $end
$upscope $end
$scope begin gen_sign_extention1ss[18] $end
$scope module sign_extention_a_inst $end
$var wire 1 I i_x $end
$var wire 1 J o_y $end
$upscope $end
$upscope $end
$scope begin gen_sign_extention1ss[19] $end
$scope module sign_extention_a_inst $end
$var wire 1 K i_x $end
$var wire 1 L o_y $end
$upscope $end
$upscope $end
$scope begin gen_sign_extention1ss[20] $end
$scope module sign_extention_a_inst $end
$var wire 1 M i_x $end
$var wire 1 N o_y $end
$upscope $end
$upscope $end
$scope begin gen_sign_extention1ss[21] $end
$scope module sign_extention_a_inst $end
$var wire 1 O i_x $end
$var wire 1 P o_y $end
$upscope $end
$upscope $end
$scope begin gen_sign_extention1ss[22] $end
$scope module sign_extention_a_inst $end
$var wire 1 Q i_x $end
$var wire 1 R o_y $end
$upscope $end
$upscope $end
$scope begin gen_sign_extention1ss[23] $end
$scope module sign_extention_a_inst $end
$var wire 1 S i_x $end
$var wire 1 T o_y $end
$upscope $end
$upscope $end
$scope begin gen_sign_extention1ss[24] $end
$scope module sign_extention_a_inst $end
$var wire 1 U i_x $end
$var wire 1 V o_y $end
$upscope $end
$upscope $end
$scope begin gen_sign_extention1ss[25] $end
$scope module sign_extention_a_inst $end
$var wire 1 W i_x $end
$var wire 1 X o_y $end
$upscope $end
$upscope $end
$scope begin gen_sign_extention1ss[26] $end
$scope module sign_extention_a_inst $end
$var wire 1 Y i_x $end
$var wire 1 Z o_y $end
$upscope $end
$upscope $end
$scope begin gen_sign_extention1ss[27] $end
$scope module sign_extention_a_inst $end
$var wire 1 [ i_x $end
$var wire 1 \ o_y $end
$upscope $end
$upscope $end
$scope begin gen_sign_extention1ss[28] $end
$scope module sign_extention_a_inst $end
$var wire 1 ] i_x $end
$var wire 1 ^ o_y $end
$upscope $end
$upscope $end
$scope begin gen_sign_extention1ss[29] $end
$scope module sign_extention_a_inst $end
$var wire 1 _ i_x $end
$var wire 1 ` o_y $end
$upscope $end
$upscope $end
$scope begin gen_sign_extention1ss[30] $end
$scope module sign_extention_a_inst $end
$var wire 1 a i_x $end
$var wire 1 b o_y $end
$upscope $end
$upscope $end
$scope begin gen_sign_extention1ss[31] $end
$scope module sign_extention_a_inst $end
$var wire 1 c i_x $end
$var wire 1 d o_y $end
$upscope $end
$upscope $end
$upscope $end
$upscope $end
$enddefinitions $end
#0
$dumpvars
0d
0c
0b
0a
0`
0_
0^
0]
0\
0[
0Z
0Y
0X
0W
0V
0U
0T
0S
0R
0Q
0P
0O
0N
0M
0L
0K
0J
0I
0H
0G
0F
0E
0D
0C
0B
0A
0@
0?
0>
0=
0<
0;
0:
09
08
07
06
05
04
03
02
01
00
0/
0.
0-
0,
0+
0*
0)
0(
0'
0&
0%
b0 $
b0 #
b0 "
b0 !
$end
#2000
b1 !
b1 $
1&
1%
b1 "
b1 #
#4000
0&
0%
b10 !
b10 $
1(
1'
b10 "
b10 #
#6000
b11 !
b11 $
1&
1%
b11 "
b11 #
#8000
0&
0%
0(
0'
b100 !
b100 $
1*
1)
b100 "
b100 #
#10000
b101 !
b101 $
1&
1%
b101 "
b101 #
#12000
0&
0%
b110 !
b110 $
1(
1'
b110 "
b110 #
#14000
b111 !
b111 $
1&
1%
b111 "
b111 #
#16000
0&
0%
0(
0'
0*
0)
b1000 !
b1000 $
1,
1+
b1000 "
b1000 #
#18000
b1001 !
b1001 $
1&
1%
b1001 "
b1001 #
#20000
0&
0%
b1010 !
b1010 $
1(
1'
b1010 "
b1010 #
#22000
b1011 !
b1011 $
1&
1%
b1011 "
b1011 #
#24000
0&
0%
0(
0'
b1100 !
b1100 $
1*
1)
b1100 "
b1100 #
#26000
b1101 !
b1101 $
1&
1%
b1101 "
b1101 #
#28000
0&
0%
b1110 !
b1110 $
1(
1'
b1110 "
b1110 #
#30000
b1111 !
b1111 $
1&
1%
b1111 "
b1111 #
#32000
0&
0%
0(
0'
0*
0)
0,
0+
b10000 !
b10000 $
1.
1-
b10000 "
b10000 #
#34000
b10001 !
b10001 $
1&
1%
b10001 "
b10001 #
#36000
0&
0%
b10010 !
b10010 $
1(
1'
b10010 "
b10010 #
#38000
b10011 !
b10011 $
1&
1%
b10011 "
b10011 #
#40000
0&
0%
0(
0'
b10100 !
b10100 $
1*
1)
b10100 "
b10100 #
#42000
b10101 !
b10101 $
1&
1%
b10101 "
b10101 #
#44000
0&
0%
b10110 !
b10110 $
1(
1'
b10110 "
b10110 #
#46000
b10111 !
b10111 $
1&
1%
b10111 "
b10111 #
#48000
0&
0%
0(
0'
0*
0)
b11000 !
b11000 $
1,
1+
b11000 "
b11000 #
#50000
b11001 !
b11001 $
1&
1%
b11001 "
b11001 #
#52000
0&
0%
b11010 !
b11010 $
1(
1'
b11010 "
b11010 #
#54000
b11011 !
b11011 $
1&
1%
b11011 "
b11011 #
#56000
0&
0%
0(
0'
b11100 !
b11100 $
1*
1)
b11100 "
b11100 #
#58000
b11101 !
b11101 $
1&
1%
b11101 "
b11101 #
#60000
0&
0%
b11110 !
b11110 $
1(
1'
b11110 "
b11110 #
#62000
b11111 !
b11111 $
1&
1%
b11111 "
b11111 #
#64000
0&
0%
0(
0'
0*
0)
0,
0+
0.
0-
b100000 !
b100000 $
10
1/
b100000 "
b100000 #
#66000
b100001 !
b100001 $
1&
1%
b100001 "
b100001 #
#68000
0&
0%
b100010 !
b100010 $
1(
1'
b100010 "
b100010 #
#70000
b100011 !
b100011 $
1&
1%
b100011 "
b100011 #
#72000
0&
0%
0(
0'
b100100 !
b100100 $
1*
1)
b100100 "
b100100 #
#74000
b100101 !
b100101 $
1&
1%
b100101 "
b100101 #
#76000
0&
0%
b100110 !
b100110 $
1(
1'
b100110 "
b100110 #
#78000
b100111 !
b100111 $
1&
1%
b100111 "
b100111 #
#80000
0&
0%
0(
0'
0*
0)
b101000 !
b101000 $
1,
1+
b101000 "
b101000 #
#82000
b101001 !
b101001 $
1&
1%
b101001 "
b101001 #
#84000
0&
0%
b101010 !
b101010 $
1(
1'
b101010 "
b101010 #
#86000
b101011 !
b101011 $
1&
1%
b101011 "
b101011 #
#88000
0&
0%
0(
0'
b101100 !
b101100 $
1*
1)
b101100 "
b101100 #
#90000
b101101 !
b101101 $
1&
1%
b101101 "
b101101 #
#92000
0&
0%
b101110 !
b101110 $
1(
1'
b101110 "
b101110 #
#94000
b101111 !
b101111 $
1&
1%
b101111 "
b101111 #
#96000
0&
0%
0(
0'
0*
0)
0,
0+
b110000 !
b110000 $
1.
1-
b110000 "
b110000 #
#98000
b110001 !
b110001 $
1&
1%
b110001 "
b110001 #
#100000
0&
0%
b110010 !
b110010 $
1(
1'
b110010 "
b110010 #
#102000
b110011 !
b110011 $
1&
1%
b110011 "
b110011 #
#104000
0&
0%
0(
0'
b110100 !
b110100 $
1*
1)
b110100 "
b110100 #
#106000
b110101 !
b110101 $
1&
1%
b110101 "
b110101 #
#108000
0&
0%
b110110 !
b110110 $
1(
1'
b110110 "
b110110 #
#110000
b110111 !
b110111 $
1&
1%
b110111 "
b110111 #
#112000
0&
0%
0(
0'
0*
0)
b111000 !
b111000 $
1,
1+
b111000 "
b111000 #
#114000
b111001 !
b111001 $
1&
1%
b111001 "
b111001 #
#116000
0&
0%
b111010 !
b111010 $
1(
1'
b111010 "
b111010 #
#118000
b111011 !
b111011 $
1&
1%
b111011 "
b111011 #
#120000
0&
0%
0(
0'
b111100 !
b111100 $
1*
1)
b111100 "
b111100 #
#122000
b111101 !
b111101 $
1&
1%
b111101 "
b111101 #
#124000
0&
0%
b111110 !
b111110 $
1(
1'
b111110 "
b111110 #
#126000
b111111 !
b111111 $
1&
1%
b111111 "
b111111 #
#128000
0&
0%
0(
0'
0*
0)
0,
0+
0.
0-
00
0/
b1000000 !
b1000000 $
12
11
b1000000 "
b1000000 #
#130000
b1000001 !
b1000001 $
1&
1%
b1000001 "
b1000001 #
#132000
0&
0%
b1000010 !
b1000010 $
1(
1'
b1000010 "
b1000010 #
#134000
b1000011 !
b1000011 $
1&
1%
b1000011 "
b1000011 #
#136000
0&
0%
0(
0'
b1000100 !
b1000100 $
1*
1)
b1000100 "
b1000100 #
#138000
b1000101 !
b1000101 $
1&
1%
b1000101 "
b1000101 #
#140000
0&
0%
b1000110 !
b1000110 $
1(
1'
b1000110 "
b1000110 #
#142000
b1000111 !
b1000111 $
1&
1%
b1000111 "
b1000111 #
#144000
0&
0%
0(
0'
0*
0)
b1001000 !
b1001000 $
1,
1+
b1001000 "
b1001000 #
#146000
b1001001 !
b1001001 $
1&
1%
b1001001 "
b1001001 #
#148000
0&
0%
b1001010 !
b1001010 $
1(
1'
b1001010 "
b1001010 #
#150000
b1001011 !
b1001011 $
1&
1%
b1001011 "
b1001011 #
#152000
0&
0%
0(
0'
b1001100 !
b1001100 $
1*
1)
b1001100 "
b1001100 #
#154000
b1001101 !
b1001101 $
1&
1%
b1001101 "
b1001101 #
#156000
0&
0%
b1001110 !
b1001110 $
1(
1'
b1001110 "
b1001110 #
#158000
b1001111 !
b1001111 $
1&
1%
b1001111 "
b1001111 #
#160000
0&
0%
0(
0'
0*
0)
0,
0+
b1010000 !
b1010000 $
1.
1-
b1010000 "
b1010000 #
#162000
b1010001 !
b1010001 $
1&
1%
b1010001 "
b1010001 #
#164000
0&
0%
b1010010 !
b1010010 $
1(
1'
b1010010 "
b1010010 #
#166000
b1010011 !
b1010011 $
1&
1%
b1010011 "
b1010011 #
#168000
0&
0%
0(
0'
b1010100 !
b1010100 $
1*
1)
b1010100 "
b1010100 #
#170000
b1010101 !
b1010101 $
1&
1%
b1010101 "
b1010101 #
#172000
0&
0%
b1010110 !
b1010110 $
1(
1'
b1010110 "
b1010110 #
#174000
b1010111 !
b1010111 $
1&
1%
b1010111 "
b1010111 #
#176000
0&
0%
0(
0'
0*
0)
b1011000 !
b1011000 $
1,
1+
b1011000 "
b1011000 #
#178000
b1011001 !
b1011001 $
1&
1%
b1011001 "
b1011001 #
#180000
0&
0%
b1011010 !
b1011010 $
1(
1'
b1011010 "
b1011010 #
#182000
b1011011 !
b1011011 $
1&
1%
b1011011 "
b1011011 #
#184000
0&
0%
0(
0'
b1011100 !
b1011100 $
1*
1)
b1011100 "
b1011100 #
#186000
b1011101 !
b1011101 $
1&
1%
b1011101 "
b1011101 #
#188000
0&
0%
b1011110 !
b1011110 $
1(
1'
b1011110 "
b1011110 #
#190000
b1011111 !
b1011111 $
1&
1%
b1011111 "
b1011111 #
#192000
0&
0%
0(
0'
0*
0)
0,
0+
0.
0-
b1100000 !
b1100000 $
10
1/
b1100000 "
b1100000 #
#194000
b1100001 !
b1100001 $
1&
1%
b1100001 "
b1100001 #
#196000
0&
0%
b1100010 !
b1100010 $
1(
1'
b1100010 "
b1100010 #
#198000
b1100011 !
b1100011 $
1&
1%
b1100011 "
b1100011 #
#200000
0&
0%
0(
0'
b1100100 !
b1100100 $
1*
1)
b1100100 "
b1100100 #
#202000
b1100101 !
b1100101 $
1&
1%
b1100101 "
b1100101 #
#204000
0&
0%
b1100110 !
b1100110 $
1(
1'
b1100110 "
b1100110 #
#206000
b1100111 !
b1100111 $
1&
1%
b1100111 "
b1100111 #
#208000
0&
0%
0(
0'
0*
0)
b1101000 !
b1101000 $
1,
1+
b1101000 "
b1101000 #
#210000
b1101001 !
b1101001 $
1&
1%
b1101001 "
b1101001 #
#212000
0&
0%
b1101010 !
b1101010 $
1(
1'
b1101010 "
b1101010 #
#214000
b1101011 !
b1101011 $
1&
1%
b1101011 "
b1101011 #
#216000
0&
0%
0(
0'
b1101100 !
b1101100 $
1*
1)
b1101100 "
b1101100 #
#218000
b1101101 !
b1101101 $
1&
1%
b1101101 "
b1101101 #
#220000
0&
0%
b1101110 !
b1101110 $
1(
1'
b1101110 "
b1101110 #
#222000
b1101111 !
b1101111 $
1&
1%
b1101111 "
b1101111 #
#224000
0&
0%
0(
0'
0*
0)
0,
0+
b1110000 !
b1110000 $
1.
1-
b1110000 "
b1110000 #
#226000
b1110001 !
b1110001 $
1&
1%
b1110001 "
b1110001 #
#228000
0&
0%
b1110010 !
b1110010 $
1(
1'
b1110010 "
b1110010 #
#230000
b1110011 !
b1110011 $
1&
1%
b1110011 "
b1110011 #
#232000
0&
0%
0(
0'
b1110100 !
b1110100 $
1*
1)
b1110100 "
b1110100 #
#234000
b1110101 !
b1110101 $
1&
1%
b1110101 "
b1110101 #
#236000
0&
0%
b1110110 !
b1110110 $
1(
1'
b1110110 "
b1110110 #
#238000
b1110111 !
b1110111 $
1&
1%
b1110111 "
b1110111 #
#240000
0&
0%
0(
0'
0*
0)
b1111000 !
b1111000 $
1,
1+
b1111000 "
b1111000 #
#242000
b1111001 !
b1111001 $
1&
1%
b1111001 "
b1111001 #
#244000
0&
0%
b1111010 !
b1111010 $
1(
1'
b1111010 "
b1111010 #
#246000
b1111011 !
b1111011 $
1&
1%
b1111011 "
b1111011 #
#248000
0&
0%
0(
0'
b1111100 !
b1111100 $
1*
1)
b1111100 "
b1111100 #
#250000
b1111101 !
b1111101 $
1&
1%
b1111101 "
b1111101 #
#252000
0&
0%
b1111110 !
b1111110 $
1(
1'
b1111110 "
b1111110 #
#254000
b1111111 !
b1111111 $
1&
1%
b1111111 "
b1111111 #
#256000
0&
0%
0(
0'
0*
0)
0,
0+
0.
0-
00
0/
02
01
b10000000 !
b10000000 $
14
13
b10000000 "
b10000000 #
#258000
b10000001 !
b10000001 $
1&
1%
b10000001 "
b10000001 #
#260000
0&
0%
b10000010 !
b10000010 $
1(
1'
b10000010 "
b10000010 #
#262000
b10000011 !
b10000011 $
1&
1%
b10000011 "
b10000011 #
#264000
0&
0%
0(
0'
b10000100 !
b10000100 $
1*
1)
b10000100 "
b10000100 #
#266000
b10000101 !
b10000101 $
1&
1%
b10000101 "
b10000101 #
#268000
0&
0%
b10000110 !
b10000110 $
1(
1'
b10000110 "
b10000110 #
#270000
b10000111 !
b10000111 $
1&
1%
b10000111 "
b10000111 #
#272000
0&
0%
0(
0'
0*
0)
b10001000 !
b10001000 $
1,
1+
b10001000 "
b10001000 #
#274000
b10001001 !
b10001001 $
1&
1%
b10001001 "
b10001001 #
#276000
0&
0%
b10001010 !
b10001010 $
1(
1'
b10001010 "
b10001010 #
#278000
b10001011 !
b10001011 $
1&
1%
b10001011 "
b10001011 #
#280000
0&
0%
0(
0'
b10001100 !
b10001100 $
1*
1)
b10001100 "
b10001100 #
#282000
b10001101 !
b10001101 $
1&
1%
b10001101 "
b10001101 #
#284000
0&
0%
b10001110 !
b10001110 $
1(
1'
b10001110 "
b10001110 #
#286000
b10001111 !
b10001111 $
1&
1%
b10001111 "
b10001111 #
#288000
0&
0%
0(
0'
0*
0)
0,
0+
b10010000 !
b10010000 $
1.
1-
b10010000 "
b10010000 #
#290000
b10010001 !
b10010001 $
1&
1%
b10010001 "
b10010001 #
#292000
0&
0%
b10010010 !
b10010010 $
1(
1'
b10010010 "
b10010010 #
#294000
b10010011 !
b10010011 $
1&
1%
b10010011 "
b10010011 #
#296000
0&
0%
0(
0'
b10010100 !
b10010100 $
1*
1)
b10010100 "
b10010100 #
#298000
b10010101 !
b10010101 $
1&
1%
b10010101 "
b10010101 #
#300000
0&
0%
b10010110 !
b10010110 $
1(
1'
b10010110 "
b10010110 #
#302000
b10010111 !
b10010111 $
1&
1%
b10010111 "
b10010111 #
#304000
0&
0%
0(
0'
0*
0)
b10011000 !
b10011000 $
1,
1+
b10011000 "
b10011000 #
#306000
b10011001 !
b10011001 $
1&
1%
b10011001 "
b10011001 #
#308000
0&
0%
b10011010 !
b10011010 $
1(
1'
b10011010 "
b10011010 #
#310000
b10011011 !
b10011011 $
1&
1%
b10011011 "
b10011011 #
#312000
0&
0%
0(
0'
b10011100 !
b10011100 $
1*
1)
b10011100 "
b10011100 #
#314000
b10011101 !
b10011101 $
1&
1%
b10011101 "
b10011101 #
#316000
0&
0%
b10011110 !
b10011110 $
1(
1'
b10011110 "
b10011110 #
#318000
b10011111 !
b10011111 $
1&
1%
b10011111 "
b10011111 #
#320000
0&
0%
0(
0'
0*
0)
0,
0+
0.
0-
b10100000 !
b10100000 $
10
1/
b10100000 "
b10100000 #
#322000
b10100001 !
b10100001 $
1&
1%
b10100001 "
b10100001 #
#324000
0&
0%
b10100010 !
b10100010 $
1(
1'
b10100010 "
b10100010 #
#326000
b10100011 !
b10100011 $
1&
1%
b10100011 "
b10100011 #
#328000
0&
0%
0(
0'
b10100100 !
b10100100 $
1*
1)
b10100100 "
b10100100 #
#330000
b10100101 !
b10100101 $
1&
1%
b10100101 "
b10100101 #
#332000
0&
0%
b10100110 !
b10100110 $
1(
1'
b10100110 "
b10100110 #
#334000
b10100111 !
b10100111 $
1&
1%
b10100111 "
b10100111 #
#336000
0&
0%
0(
0'
0*
0)
b10101000 !
b10101000 $
1,
1+
b10101000 "
b10101000 #
#338000
b10101001 !
b10101001 $
1&
1%
b10101001 "
b10101001 #
#340000
0&
0%
b10101010 !
b10101010 $
1(
1'
b10101010 "
b10101010 #
#342000
b10101011 !
b10101011 $
1&
1%
b10101011 "
b10101011 #
#344000
0&
0%
0(
0'
b10101100 !
b10101100 $
1*
1)
b10101100 "
b10101100 #
#346000
b10101101 !
b10101101 $
1&
1%
b10101101 "
b10101101 #
#348000
0&
0%
b10101110 !
b10101110 $
1(
1'
b10101110 "
b10101110 #
#350000
b10101111 !
b10101111 $
1&
1%
b10101111 "
b10101111 #
#352000
0&
0%
0(
0'
0*
0)
0,
0+
b10110000 !
b10110000 $
1.
1-
b10110000 "
b10110000 #
#354000
b10110001 !
b10110001 $
1&
1%
b10110001 "
b10110001 #
#356000
0&
0%
b10110010 !
b10110010 $
1(
1'
b10110010 "
b10110010 #
#358000
b10110011 !
b10110011 $
1&
1%
b10110011 "
b10110011 #
#360000
0&
0%
0(
0'
b10110100 !
b10110100 $
1*
1)
b10110100 "
b10110100 #
#362000
b10110101 !
b10110101 $
1&
1%
b10110101 "
b10110101 #
#364000
0&
0%
b10110110 !
b10110110 $
1(
1'
b10110110 "
b10110110 #
#366000
b10110111 !
b10110111 $
1&
1%
b10110111 "
b10110111 #
#368000
0&
0%
0(
0'
0*
0)
b10111000 !
b10111000 $
1,
1+
b10111000 "
b10111000 #
#370000
b10111001 !
b10111001 $
1&
1%
b10111001 "
b10111001 #
#372000
0&
0%
b10111010 !
b10111010 $
1(
1'
b10111010 "
b10111010 #
#374000
b10111011 !
b10111011 $
1&
1%
b10111011 "
b10111011 #
#376000
0&
0%
0(
0'
b10111100 !
b10111100 $
1*
1)
b10111100 "
b10111100 #
#378000
b10111101 !
b10111101 $
1&
1%
b10111101 "
b10111101 #
#380000
0&
0%
b10111110 !
b10111110 $
1(
1'
b10111110 "
b10111110 #
#382000
b10111111 !
b10111111 $
1&
1%
b10111111 "
b10111111 #
#384000
0&
0%
0(
0'
0*
0)
0,
0+
0.
0-
00
0/
b11000000 !
b11000000 $
12
11
b11000000 "
b11000000 #
#386000
b11000001 !
b11000001 $
1&
1%
b11000001 "
b11000001 #
#388000
0&
0%
b11000010 !
b11000010 $
1(
1'
b11000010 "
b11000010 #
#390000
b11000011 !
b11000011 $
1&
1%
b11000011 "
b11000011 #
#392000
0&
0%
0(
0'
b11000100 !
b11000100 $
1*
1)
b11000100 "
b11000100 #
#394000
b11000101 !
b11000101 $
1&
1%
b11000101 "
b11000101 #
#396000
0&
0%
b11000110 !
b11000110 $
1(
1'
b11000110 "
b11000110 #
#398000
b11000111 !
b11000111 $
1&
1%
b11000111 "
b11000111 #
#400000
0&
0%
0(
0'
0*
0)
b11001000 !
b11001000 $
1,
1+
b11001000 "
b11001000 #
#402000
b11001001 !
b11001001 $
1&
1%
b11001001 "
b11001001 #
#404000
0&
0%
b11001010 !
b11001010 $
1(
1'
b11001010 "
b11001010 #
#406000
b11001011 !
b11001011 $
1&
1%
b11001011 "
b11001011 #
#408000
0&
0%
0(
0'
b11001100 !
b11001100 $
1*
1)
b11001100 "
b11001100 #
#410000
b11001101 !
b11001101 $
1&
1%
b11001101 "
b11001101 #
#412000
0&
0%
b11001110 !
b11001110 $
1(
1'
b11001110 "
b11001110 #
#414000
b11001111 !
b11001111 $
1&
1%
b11001111 "
b11001111 #
#416000
0&
0%
0(
0'
0*
0)
0,
0+
b11010000 !
b11010000 $
1.
1-
b11010000 "
b11010000 #
#418000
b11010001 !
b11010001 $
1&
1%
b11010001 "
b11010001 #
#420000
0&
0%
b11010010 !
b11010010 $
1(
1'
b11010010 "
b11010010 #
#422000
b11010011 !
b11010011 $
1&
1%
b11010011 "
b11010011 #
#424000
0&
0%
0(
0'
b11010100 !
b11010100 $
1*
1)
b11010100 "
b11010100 #
#426000
b11010101 !
b11010101 $
1&
1%
b11010101 "
b11010101 #
#428000
0&
0%
b11010110 !
b11010110 $
1(
1'
b11010110 "
b11010110 #
#430000
b11010111 !
b11010111 $
1&
1%
b11010111 "
b11010111 #
#432000
0&
0%
0(
0'
0*
0)
b11011000 !
b11011000 $
1,
1+
b11011000 "
b11011000 #
#434000
b11011001 !
b11011001 $
1&
1%
b11011001 "
b11011001 #
#436000
0&
0%
b11011010 !
b11011010 $
1(
1'
b11011010 "
b11011010 #
#438000
b11011011 !
b11011011 $
1&
1%
b11011011 "
b11011011 #
#440000
0&
0%
0(
0'
b11011100 !
b11011100 $
1*
1)
b11011100 "
b11011100 #
#442000
b11011101 !
b11011101 $
1&
1%
b11011101 "
b11011101 #
#444000
0&
0%
b11011110 !
b11011110 $
1(
1'
b11011110 "
b11011110 #
#446000
b11011111 !
b11011111 $
1&
1%
b11011111 "
b11011111 #
#448000
0&
0%
0(
0'
0*
0)
0,
0+
0.
0-
b11100000 !
b11100000 $
10
1/
b11100000 "
b11100000 #
#450000
b11100001 !
b11100001 $
1&
1%
b11100001 "
b11100001 #
#452000
0&
0%
b11100010 !
b11100010 $
1(
1'
b11100010 "
b11100010 #
#454000
b11100011 !
b11100011 $
1&
1%
b11100011 "
b11100011 #
#456000
0&
0%
0(
0'
b11100100 !
b11100100 $
1*
1)
b11100100 "
b11100100 #
#458000
b11100101 !
b11100101 $
1&
1%
b11100101 "
b11100101 #
#460000
0&
0%
b11100110 !
b11100110 $
1(
1'
b11100110 "
b11100110 #
#462000
b11100111 !
b11100111 $
1&
1%
b11100111 "
b11100111 #
#464000
0&
0%
0(
0'
0*
0)
b11101000 !
b11101000 $
1,
1+
b11101000 "
b11101000 #
#466000
b11101001 !
b11101001 $
1&
1%
b11101001 "
b11101001 #
#468000
0&
0%
b11101010 !
b11101010 $
1(
1'
b11101010 "
b11101010 #
#470000
b11101011 !
b11101011 $
1&
1%
b11101011 "
b11101011 #
#472000
0&
0%
0(
0'
b11101100 !
b11101100 $
1*
1)
b11101100 "
b11101100 #
#474000
b11101101 !
b11101101 $
1&
1%
b11101101 "
b11101101 #
#476000
0&
0%
b11101110 !
b11101110 $
1(
1'
b11101110 "
b11101110 #
#478000
b11101111 !
b11101111 $
1&
1%
b11101111 "
b11101111 #
#480000
0&
0%
0(
0'
0*
0)
0,
0+
b11110000 !
b11110000 $
1.
1-
b11110000 "
b11110000 #
#482000
b11110001 !
b11110001 $
1&
1%
b11110001 "
b11110001 #
#484000
0&
0%
b11110010 !
b11110010 $
1(
1'
b11110010 "
b11110010 #
#486000
b11110011 !
b11110011 $
1&
1%
b11110011 "
b11110011 #
#488000
0&
0%
0(
0'
b11110100 !
b11110100 $
1*
1)
b11110100 "
b11110100 #
#490000
b11110101 !
b11110101 $
1&
1%
b11110101 "
b11110101 #
#492000
0&
0%
b11110110 !
b11110110 $
1(
1'
b11110110 "
b11110110 #
#494000
b11110111 !
b11110111 $
1&
1%
b11110111 "
b11110111 #
#496000
0&
0%
0(
0'
0*
0)
b11111000 !
b11111000 $
1,
1+
b11111000 "
b11111000 #
#498000
b11111001 !
b11111001 $
1&
1%
b11111001 "
b11111001 #
#500000
0&
0%
b11111010 !
b11111010 $
1(
1'
b11111010 "
b11111010 #
#502000
b11111011 !
b11111011 $
1&
1%
b11111011 "
b11111011 #
#504000
0&
0%
0(
0'
b11111100 !
b11111100 $
1*
1)
b11111100 "
b11111100 #
#506000
b11111101 !
b11111101 $
1&
1%
b11111101 "
b11111101 #
#508000
0&
0%
b11111110 !
b11111110 $
1(
1'
b11111110 "
b11111110 #
#510000
b11111111 !
b11111111 $
1&
1%
b11111111 "
b11111111 #
#512000
0&
0%
0(
0'
0*
0)
0,
0+
0.
0-
00
0/
02
01
04
03
b100000000 !
b100000000 $
16
15
b100000000 "
b100000000 #
#514000
b100000001 !
b100000001 $
1&
1%
b100000001 "
b100000001 #
#516000
0&
0%
b100000010 !
b100000010 $
1(
1'
b100000010 "
b100000010 #
#518000
b100000011 !
b100000011 $
1&
1%
b100000011 "
b100000011 #
#520000
0&
0%
0(
0'
b100000100 !
b100000100 $
1*
1)
b100000100 "
b100000100 #
#522000
b100000101 !
b100000101 $
1&
1%
b100000101 "
b100000101 #
#524000
0&
0%
b100000110 !
b100000110 $
1(
1'
b100000110 "
b100000110 #
#526000
b100000111 !
b100000111 $
1&
1%
b100000111 "
b100000111 #
#528000
0&
0%
0(
0'
0*
0)
b100001000 !
b100001000 $
1,
1+
b100001000 "
b100001000 #
#530000
b100001001 !
b100001001 $
1&
1%
b100001001 "
b100001001 #
#532000
0&
0%
b100001010 !
b100001010 $
1(
1'
b100001010 "
b100001010 #
#534000
b100001011 !
b100001011 $
1&
1%
b100001011 "
b100001011 #
